.DS_Store
.dockerignore
.git/COMMIT_EDITMSG
.git/HEAD
.git/config
.git/description
.git/hooks/applypatch-msg.sample
.git/hooks/commit-msg.sample
.git/hooks/fsmonitor-watchman.sample
.git/hooks/post-update.sample
.git/hooks/pre-applypatch.sample
.git/hooks/pre-commit.sample
.git/hooks/pre-merge-commit.sample
.git/hooks/pre-push.sample
.git/hooks/pre-rebase.sample
.git/hooks/pre-receive.sample
.git/hooks/prepare-commit-msg.sample
.git/hooks/push-to-checkout.sample
.git/hooks/update.sample
.git/index
.git/info/exclude
.git/logs/HEAD
.git/logs/refs/heads/main
.git/logs/refs/remotes/origin/HEAD
.git/logs/refs/remotes/origin/main
.git/objects/01/31dee21388b60a1fe38f60d83b6871b2c4a82e
.git/objects/07/06ae5e1463600aa1ca6325a631e788eeff5156
.git/objects/0f/c54d5b91f134c8d3eee768b2ed4a3924a81902
.git/objects/10/16d07a81681a26f19afb177da213927ba88887
.git/objects/12/53169167c6c4c54821809f2357f59310262eae
.git/objects/28/6c42857c6681df6c35768a05e366b8dec08f9a
.git/objects/29/22f27ce91b25f400303573968c9da26ad213b9
.git/objects/2e/ea525d885d5148108f6f3a9a8613863f783d36
.git/objects/32/bdbe4561da93d68266a2637480a15ce2de5f4f
.git/objects/39/b6a1675ddf3d507fdccc43b007bbb58cb4bfcb
.git/objects/3a/503ff29258acc4d5283427c40a7d9e0847d11b
.git/objects/40/1e3bbe21c64fadeec796c7e96807911c194ce4
.git/objects/54/1e597bdd54d340a76805446d55e897e0182c68
.git/objects/54/3a68c676b10e7d08ca49954712790b85b6b0d1
.git/objects/54/c66be5a31ee0d26f590b0e76f8fd41ec8f68fe
.git/objects/55/11912e25d1d8a5a1708bd58c5f700134231d0e
.git/objects/59/04a627cb98508ead4bfae9ba5f58234c1b80e8
.git/objects/5c/dd259318b238c85f4822179e1e46f551d86b60
.git/objects/5e/fc411c3cb7c875f664e58f7f346aa3f933169d
.git/objects/61/fbf48ac583e777f26c5b052872a7cde1532acf
.git/objects/67/3bdef2d249a5728119a142f829149d4b72a9fa
.git/objects/6c/e22b9166c62de7084ffb5f1eb7e9aa7ca9d472
.git/objects/70/d969facbfe6195413f4cfef033c357450fc5eb
.git/objects/7b/f128844df9a159b3d274e53269fb78a3dc9045
application_gces_douglasmonteles-0.1.0.dist-info/LICENSE
application_gces_douglasmonteles-0.1.0.dist-info/WHEEL
application_gces_douglasmonteles-0.1.0.dist-info/METADATA
application_gces_douglasmonteles-0.1.0.dist-info/RECORD
